Workbook

Sheet 项目信息
A1: 序号 | B1: 类别 | C1: 名称 | D1: 单位 | E1: 数值
B2: 项目信息 | C2: 客户姓名： | E2: 张先生
B3: 项目信息 | C3: 安装地点： | E3: 蔡甸
B4: 项目信息 | C4: 客户电话： | E4: 134
B5: 项目信息 | C5: 销售经理： | E5: 王
C6: 销售经理电话： | E6: 155
B7: 项目信息 | C7: 安装高度 | D7: m | E7: 3
B8: 项目信息 | C8: 安装形式 | E8: 钢结构-双坡
B9: 项目信息 | C9: 排布方式 | E9: 竖向排布
B10: 项目信息 | C10: 并网电压： | D10: V | E10: 380
B11: 光伏系统 | C11: 组件功率 | D11: W | E11: 650
B12: 光伏系统 | C12: 组件尺寸-长 | D12: mm | E12: =IF(E11=345,1689,IF(E11=540,2279,IF(E11=650,2382))) -> 2382
B13: 光伏系统 | C13: 组件尺寸-宽 | D13: mm | E13: =IF(E11=345,996,IF(E11=540,1134,IF(E11=650,1134))) -> 1134
B14: 光伏系统 | C14: 组件尺寸-高 | D14: mm | E14: =IF(E11=345,35,IF(E11=540,35,IF(E11=650,30))) -> 30
B15: 光伏系统 | C15: 1坡安装数量-行 | D15: 行 | E15: 2
B16: 光伏系统 | C16: 1坡安装数量-列 | D16: 列 | E16: 5
B17: 光伏系统 | C17: 2坡安装数量-行 | D17: 行 | E17: 3
B18: 光伏系统 | C18: 2坡安装数量-列 | D18: 列 | E18: 5
B19: 光伏系统 | C19: 总安装数量 | D19: 块 | E19: =E15*E16+E17*E18 -> 25
B20: 光伏系统 | C20: 安装面积 | D20: ㎡ | E20: =E12*E13*E19/1000000 -> 67.5297
B21: 光伏系统 | C21: 安装功率 | D21: KW | E21: =E19*E11/1000 -> 16.25
B22: 钢结构 | C22: 钢结构形式 | E22: 叠焊
B23: 钢结构 | C23: 喷漆 | E23: 磁漆
B24: 电气系统 | C24: 交流线 | D24: m | E24: 50
B25: 电气系统 | C25: 直流线 | D25: m | E25: 100

Sheet 报价单
B2: 分布式光伏电站报价单
B3: 报价日期： | J3: =TODAY() -> 46215
B4: 客户信息 | F4: 服务方信息
B5: 联 系 人： | D5: =项目信息!E2 -> 张先生 | E5: ="客户电话："&项目信息!E4 -> 客户电话：134 | F5: 联 系 人： | H5: =项目信息!E5 -> 王 | I5: 联系电话： | J5: =项目信息!E6 -> 155
B6: 项目地址： | D6: =项目信息!E3 -> 蔡甸 | F6: 联系地址：
B8: 安装面积： | D8: =项目信息!E20&"㎡" -> 67.5297㎡ | E8: ="安装功率："&项目信息!E21&"Kw" -> 安装功率：16.25Kw | F8: 预计年发电量： | H8: =项目信息!E21*1000&"度左右" -> 16250度左右
B9: 以下为贵方询价产品明细，请详阅：如有疑问，请及时与我司联系，谢谢！
B10: 报 价 栏
B11: 序号 | C11: 类别 | D11: 产品名称 | E11: 规格型号 | F11: 单位 | G11: 数量 | H11: 单价 | I11: 金额 | J11: 备注
B12: 01 | C12: 光伏系统 | D12: 光伏组件 | E12: 隆基650W 单晶硅 双玻 | F12: 块 | G12: =项目信息!E19 -> 25 | H12: =项目信息!E11*0.9 -> 585 | I12: =G12*H12 -> 14625
B13: 02 | C13: 光伏系统 | D13: 逆变器 | E13: 固德威 10Kw 380V | F13: 台 | G13: 1 | H13: =IF(项目信息!E21<=20,2800,IF(20<项目信息!E21<=30,3500,IF(20<项目信息!E21>30=650,2382))) -> 2800 | I13: =G13*H13 -> 2800
B14: 03 | C14: 光伏系统 | D14: 配电箱 | E14: 380V 15KWw | F14: 台 | G14: 1 | H14: =IF(项目信息!E21<=20,500,IF(20<项目信息!E21<=30,900,IF(20<项目信息!E21>30,1500))) -> 500 | I14: =G14*H14 -> 500
B15: 04 | C15: 光伏系统 | D15: 交流线缆 | E15: YJV-3*6+2*4 | F15: 米 | G15: =项目信息!E24 -> 50 | H15: 35 | I15: =G15*H15 -> 1750 | J15: 预计50米，方案确定后多退少补
B16: 05 | C16: 光伏系统 | D16: 直流线缆 | E16: 光伏专用直流线 | F16: 米 | G16: =项目信息!E25 -> 100 | H16: 6 | I16: =G16*H16 -> 600 | J16: 预计红黑线各100米，方案确定后多退少补
B17: 06 | C17: 光伏系统 | D17: 防水结构 | E17: M型 锌镁铝支架 +铝合金压块+铝合金盖板 | F17: m² | G17: =项目信息!E20 -> 67.5297 | H17: 65 | I17: =G17*H17 -> 4389.4305
B18: 07 | C18: 光伏系统 | D18: 辅料及安装 | E18: 光伏板和防水结构安装及辅料 | F18: m² | G18: =项目信息!E20 -> 67.5297 | H18: 45 | I18: =G18*H18 -> 3038.8365
B19: 08 | C19: 光伏系统 | D19: 线路安装 | E19: 走线、逆变器、配电箱安装及辅材 | F19: m² | G19: =项目信息!E20 -> 67.5297 | H19: 15 | I19: =G19*H19 -> 1012.9455
B20: 09 | C20: 钢结构 | D20: 施工及材料 | E20: 钢结构施工，材料100*100*2.5立柱，热镀锌钢材，辅料 | F20: m² | G20: =项目信息!E20 -> 67.5297 | H20: =IF(项目信息!E22="平焊",145,IF(项目信息!E22="叠焊",195,IF(项目信息!E22="瓦面平铺",110,0))) -> 195 | I20: =G20*H20 -> 13168.291 | J20: =项目信息!E22 -> 叠焊
B21: 10 | C21: 钢结构 | D21: 钢结构油漆 | E21: 油漆及人工 | F21: m² | G21: =项目信息!E20 -> 67.5297 | H21: =IF(项目信息!E23="否",0,IF(项目信息!E23="磁漆",30,IF(项目信息!E23="氟碳漆",100))) -> 30 | I21: =G21*H21 -> 2025.891 | J21: =项目信息!E23 -> 磁漆
B22: 11 | C22: 其他 | D22: 并网 | E22: 电网规约四可设备及安装调试 | F22: 台 | G22: 1 | H22: 950 | I22: =G22*H22 -> 950
B23: 12 | C23: 其他 | D23: 运输及上楼 | E23: 材料运费及吊装费 | F23: 次 | G23: 1 | H23: 1400 | I23: =G23*H23 -> 1400
B24: 13 | C24: 其他 | D24: 设计费 | E24: 效果图、施工图 | F24: m² | G24: 35.96 | H24: 15 | I24: =G24*H24 -> 539.4
B25: 14 | C25: 其他 | D25: 备案及并网 | E25: 发改委备案及电网并网 | F25: 次 | G25: 1 | H25: 1000 | I25: =G25*H25 -> 1000
B26: 15
B27: 16 | E27: 价格总计： | I27: =SUM(I12:I26) -> 47799.795 | J27: 不含税
B28: 报价说明：此报价不含税
B29: （1） | C29: 报价有效期：自报价之日起10天。
B30: （2） | C30: 结算方式：预付30%的定金，货到之日付30%，安装完成之日付30%，电站并网成功起3日内付清10%尾款。
B31: （3） | C31: 交货时间：与合同签订后10个工作日内。
B32: （4） | C32: 付款方式：一般产品为30%预付款，储能及特殊型号产品预付款方式请垂询。

Sheet 组件
A1: 平面光伏瓦-多晶275
A2: 平面光伏瓦-单晶310
A3: 平面光伏瓦-单晶320
A4: 晶澳组件-Prec单晶335
A5: 晶澳组件-单晶310
A6: 晶澳组件-多晶275
A7: 晶澳组件-多晶270
